Metadata-Version: 2.1
Name: macrometa-target-oracle
Version: 1.0.0
Summary: Macrometa target connector for writing data into Oracle DB.
License: Apache-2.0
Keywords: ELT,Connectors,Workflows,Macrometa,Target,OracleDB
Author: Macrometa
Author-email: info@macrometa.com
Requires-Python: >=3.8.1,<3.11
Classifier: License :: OSI Approved :: Apache Software License
Classifier: Operating System :: OS Independent
Classifier: Programming Language :: Python :: 3
Classifier: Programming Language :: Python :: 3.9
Classifier: Programming Language :: Python :: 3.10
Classifier: Programming Language :: Python :: 3
Classifier: Programming Language :: Python :: 3.9
Requires-Dist: c8connector (>=0.0.29)
Requires-Dist: inflection (==0.3.1)
Requires-Dist: joblib (==1.2.0)
Requires-Dist: oracledb (>=1.2.2,<2.0.0)
Requires-Dist: pipelinewise-singer-python (==1.2.0)
Requires-Dist: prometheus-client (==0.16.0)
Requires-Dist: sqlalchemy (>=1.4,<2.0)
Project-URL: Bug Tracker, https://github.com/Macrometacorp/macrometa-target-oracle/issues
Project-URL: Homepage, https://www.macrometa.com/
